shell_history_analysis/__init__.py
shell_history_analysis/analyze.py
shell_history_analysis/cli.py
shell_history_analysis/shell_io.py
shell_history_analysis-0.1.3.dist-info/LICENSE
shell_history_analysis-0.1.3.dist-info/METADATA
shell_history_analysis-0.1.3.dist-info/WHEEL
shell_history_analysis-0.1.3.dist-info/entry_points.txt
shell_history_analysis-0.1.3.dist-info/top_level.txt
shell_history_analysis-0.1.3.dist-info/zip-safe
shell_history_analysis-0.1.3.dist-info/RECORD
