Metadata-Version: 2.1
Name: shell-history-analysis
Version: 0.1.3
Summary: Analyze the history of a shell
Home-page: https://github.com/MartinThoma/shell-history-analysis
Author: Martin Thoma
Author-email: info@martin-thoma.de
Maintainer: Martin Thoma
Maintainer-email: info@martin-thoma.de
License: MIT
Download-URL: https://github.com/MartinThoma/shell-history-analysis
Keywords: utility
Platform: Linux
Classifier: Development Status :: 3 - Alpha
Classifier: Environment :: Console
Classifier: Intended Audience :: Developers
Classifier: Intended Audience :: Information Technology
Classifier: License :: OSI Approved :: MIT License
Classifier: Natural Language :: English
Classifier: Programming Language :: Python :: 3.6
Classifier: Programming Language :: Python :: 3.7
Classifier: Programming Language :: Python :: 3.8
Classifier: Topic :: Software Development
Classifier: Topic :: Utilities
Requires-Dist: click
Requires-Dist: python-dateutil
Requires-Dist: matplotlib
Requires-Dist: pandas
Requires-Dist: pyaml
